cudametro/Material_Reader.py
cudametro/__init__.py
cudametro/bench.py
cudametro/construct.py
cudametro/curie_temp.py
cudametro/dmi_3.npy
cudametro/dmi_4.npy
cudametro/dmi_6.npy
cudametro/engraph.py
cudametro/fig1_script.ipynb
cudametro/fig2_script.ipynb
cudametro/fig3_script.ipynb
cudametro/grid_bench.py
cudametro/montecarlo.py
cudametro/sample.py
cudametro/sample_config.json
cudametro/visualize.py
cudametro/deprecated/alt_mat_1_construct.py
cudametro/deprecated/cri3_analysis.py
cudametro/deprecated/dmi.py
cudametro/deprecated/double_mat.py
cudametro/deprecated/sub_construct.py
cudametro/deprecated/test_cpu.py
cudametro-1.2.8.dist-info/METADATA
cudametro-1.2.8.dist-info/WHEEL
cudametro-1.2.8.dist-info/licenses/LICENSE
cudametro-1.2.8.dist-info/RECORD
