Metadata-Version: 2.4
Name: cudametro
Version: 1.2.8
Summary: pyCUDA Metropolis Monte Carlo 2D Heisenberg Model Simulation
Project-URL: Homepage, https://github.com/arkavo/CUDA-METRO
Project-URL: Issues, https://github.com/arkavo/CUDA-METRO/issues
Author-email: Arkavo Hait <arkavohait@iisc.ac.in>, Santanu Mahapatra <santanu@iisc.ac.in>
License-File: LICENSE
Classifier: License :: OSI Approved :: Apache Software License
Classifier: Operating System :: OS Independent
Classifier: Programming Language :: Python :: 3
Requires-Python: >=3.8
